parvati/__init__.py
parvati/parvati.py
parvati-1.0.5.dist-info/METADATA
parvati-1.0.5.dist-info/WHEEL
parvati-1.0.5.dist-info/licenses/LICENSE
parvati-1.0.5.dist-info/RECORD
