Metadata-Version: 2.4
Name: parvati
Version: 1.0.5
Summary: A package to compute and analyse stellar line profiles
Project-URL: Homepage, https://github.com/mrainer74/parvati
Project-URL: Issues, https://github.com/mrainer74/parvati/issues
Author-email: Monica Rainer <monica.rainer@inaf.it>
License-Expression: GPL-3.0-or-later
License-File: LICENSE
Classifier: Operating System :: OS Independent
Classifier: Programming Language :: Python :: 3
Requires-Python: >=3.9
Requires-Dist: astropy
Requires-Dist: csaps
Requires-Dist: matplotlib
Requires-Dist: numpy
Requires-Dist: scipy
Requires-Dist: uncertainties
